ai_roi/__init__.py
endkoo_ai_roi-0.1.7.dist-info/METADATA
endkoo_ai_roi-0.1.7.dist-info/WHEEL
endkoo_ai_roi-0.1.7.dist-info/top_level.txt
endkoo_ai_roi-0.1.7.dist-info/RECORD
