Metadata-Version: 2.4
Name: endkoo-ai-roi
Version: 0.1.7
Summary: The Generative AI Profitability Framework.
Author: Denis Atlan
Project-URL: Homepage, https://www.endkoo.fr
Classifier: Programming Language :: Python :: 3
Classifier: License :: OSI Approved :: MIT License
Classifier: Operating System :: OS Independent
Requires-Python: >=3.8
